vcodeboot/__init__.py
vcodeboot/files/__init__.py
vcodeboot/files/core.py
vcodeboot/globaux/__init__.py
vcodeboot/globaux/core.py
vcodeboot/pixels/__init__.py
vcodeboot/pixels/core.py
vcodeboot/pixels/utils.py
vcodeboot-0.1.4.dist-info/METADATA
vcodeboot-0.1.4.dist-info/WHEEL
vcodeboot-0.1.4.dist-info/top_level.txt
vcodeboot-0.1.4.dist-info/RECORD
