Metadata-Version: 2.1
Name: vcodeboot
Version: 0.1.4
Summary: Fonctions de Codeboot 5.
Home-page: https://github.com/Victorio-NASCIMENTO/Fonctions_Codeboot/tree/main
Author: Victorio N.
Author-email: victorio.nascimento@gmail.com
Classifier: Programming Language :: Python :: 3
Classifier: Operating System :: OS Independent
Classifier: Development Status :: 4 - Beta
Classifier: Intended Audience :: Education
Requires-Python: >=3.6
Requires-Dist: pygame
Requires-Dist: pymsgbox
